chains/__init__.py
chains/embeddings.py
chains/llm_proxy.py
chains/pdf_fixer.py
chains/rag.py
chains/retrieval.py
chains/serve.py
chains/vectordb_reader.py
chatur_chains-0.1.1.dist-info/METADATA
chatur_chains-0.1.1.dist-info/WHEEL
chatur_chains-0.1.1.dist-info/top_level.txt
chatur_chains-0.1.1.dist-info/RECORD
